asyncnsq/__init__.py
asyncnsq/connection.py
asyncnsq/consts.py
asyncnsq/consumer.py
asyncnsq/containers.py
asyncnsq/exceptions.py
asyncnsq/log.py
asyncnsq/nsq.py
asyncnsq/producer.py
asyncnsq/protocol.py
asyncnsq/selectors.py
asyncnsq/utils.py
asyncnsq/http/__init__.py
asyncnsq/http/auth.py
asyncnsq/http/base.py
asyncnsq/http/http_exceptions.py
asyncnsq/http/lookupd.py
asyncnsq/http/nsqd.py
asyncnsq/http/rest_producer.py
asyncnsq/http/writer.py
asyncnsq/tcp/__init__.py
asyncnsq/tcp/connection.py
asyncnsq/tcp/consts.py
asyncnsq/tcp/exceptions.py
asyncnsq/tcp/messages.py
asyncnsq/tcp/protocol.py
asyncnsq/tcp/reader.py
asyncnsq/tcp/reader_rdy.py
asyncnsq/tcp/writer.py
asyncnsq-1.2.1.dist-info/LICENSE
asyncnsq-1.2.1.dist-info/METADATA
asyncnsq-1.2.1.dist-info/WHEEL
asyncnsq-1.2.1.dist-info/top_level.txt
asyncnsq-1.2.1.dist-info/RECORD
